gongish/__init__.py
gongish/application.py
gongish/configuration.py
gongish/constants.py
gongish/exceptions.py
gongish/request.py
gongish/response.py
gongish/response_formatters.py
gongish/router.py
gongish/static.py
gongish/cli/__init__.py
gongish/cli/serve.py
gongish/helpers/__init__.py
gongish/helpers/headerset.py
gongish/helpers/lazyattr.py
gongish/helpers/wordrouter.py
gongish-1.5.0.dist-info/LICENSE
gongish-1.5.0.dist-info/METADATA
gongish-1.5.0.dist-info/WHEEL
gongish-1.5.0.dist-info/entry_points.txt
gongish-1.5.0.dist-info/top_level.txt
gongish-1.5.0.dist-info/RECORD
